jadn/__init__.py
jadn/core.py
jadn/definitions.py
jadn/utils.py
jadn/codec/__init__.py
jadn/codec/codec.py
jadn/codec/format_serialize_json.py
jadn/codec/format_validate.py
jadn/convert/__init__.py
jadn/convert/diagram_w.py
jadn/convert/html.py
jadn/convert/jas_w.py
jadn/convert/jidl.py
jadn/convert/markdown.py
jadn/convert/proto.py
jadn/convert/utils.py
jadn/data/dtheme.css
jadn/data/jadn_v2.0_schema.jadn
jadn/data/jadn_v2.0_schema.json
jadn/data/jidl.lark
jadn/transform/__init__.py
jadn/transform/resolve.py
jadn/transform/transform.py
jadn/translate/__init__.py
jadn/translate/jsonschema_w.py
jadn-0.7.5.dist-info/METADATA
jadn-0.7.5.dist-info/WHEEL
jadn-0.7.5.dist-info/top_level.txt
jadn-0.7.5.dist-info/RECORD
