Metadata-Version: 2.2
Name: jadn
Version: 0.7.5
Summary: JADN schema tools
Home-page: https://github.com/davaya/jadn-pypkg
Author: David Kemp
Author-email: dk190a@gmail.com
License: Apache License 2.0
Keywords: schema
Classifier: Programming Language :: Python :: 3
Classifier: License :: OSI Approved :: Apache Software License
Classifier: Operating System :: OS Independent
Classifier: Development Status :: 4 - Beta
Classifier: Intended Audience :: Developers
Classifier: Topic :: Software Development :: Build Tools
Requires-Dist: jsonschema
Requires-Dist: lxml
Requires-Dist: rfc3987
Requires-Dist: frozendict
